LICENSE
MANIFEST.in
README.rst
setup.cfg
setup.py
weboa/__init__.py
weboa/prepare.py
weboa/run.py
weboa.egg-info/PKG-INFO
weboa.egg-info/SOURCES.txt
weboa.egg-info/dependency_links.txt
weboa.egg-info/entry_points.txt
weboa.egg-info/not-zip-safe
weboa.egg-info/requires.txt
weboa.egg-info/top_level.txt
weboa/project/General.py
weboa/project/__init__.py
weboa/project/php.py
weboa/utils/Console_Color.py
weboa/utils/FileSystem.py
weboa/utils/Meta.py
weboa/utils/Printer.py
weboa/utils/Processing.py
weboa/utils/__init__.py
weboa_res/.DS_Store
weboa_res/__init__.py
weboa_res/misc/README.md
weboa_res/misc/gitignore
weboa_res/misc/robots.txt
weboa_res/phpfs/.htaccess
weboa_res/phpfs/_index.php
weboa_res/phpfs/auth
weboa_res/phpfs/consts
weboa_res/phpfs/controller
weboa_res/phpfs/db
weboa_res/phpfs/defs
weboa_res/phpfs/footer
weboa_res/phpfs/header
weboa_res/phpfs/index
weboa_res/phpfs/l
weboa_res/phpfs/language
weboa_res/phpfs/main
weboa_res/phpfs/router
weboa_res/phpfs/site.php
weboa_res/phpfs/test
weboa_res/pwa/README.md
weboa_res/pwa/icon-128x128.png
weboa_res/pwa/icon-144x144.png
weboa_res/pwa/icon-152x152.png
weboa_res/pwa/icon-192x192.png
weboa_res/pwa/icon-384x384.png
weboa_res/pwa/icon-512x512.png
weboa_res/pwa/icon-72x72.png
weboa_res/pwa/icon-96x96.png
weboa_res/pwa/manifest.json
weboa_res/pwa/serviceWorker.js