Metadata-Version: 2.1
Name: weboa
Version: 0.6.8
Summary: weboa is a cli tool to create templates for websites and preprocessors
Home-page: https://github.com/lonagi/weboa
Author: lonagi
Author-email: lonagi22@gmail.com
License: MIT
Project-URL: Bug Tracker, https://github.com/lonagi/weboa/issues
Project-URL: Source Code, https://github.com/lonagi/weboa
Keywords: weboa,python,general
Platform: any
Classifier: Development Status :: 2 - Pre-Alpha
Classifier: Intended Audience :: Developers
Classifier: License :: OSI Approved :: MIT License
Classifier: Operating System :: OS Independent
Classifier: Programming Language :: Python
Classifier: Programming Language :: Python :: 3.4
Classifier: Programming Language :: Python :: 3.5
Classifier: Programming Language :: Python :: 3.6
Classifier: Programming Language :: Python :: 3.7
Classifier: Programming Language :: Python :: 3.8
Classifier: Topic :: Software Development :: Libraries :: Python Modules
License-File: LICENSE
